{
  "applied_rule_ids": "2,3",
  "base_currency_code": "USD",
  "base_discount_amount": -90,
  "base_grand_total": 410,
  "base_discount_tax_compensation_amount": 0,
  "base_shipping_amount": 50,
  "base_shipping_discount_amount": 0,
  "base_shipping_discount_tax_compensation_amnt": 0,
  "base_shipping_incl_tax": 50,
  "base_shipping_tax_amount": 0,
  "base_subtotal": 450,
  "base_subtotal_incl_tax": 450,
  "base_tax_amount": 0,
  "base_total_due": 410,
  "base_to_global_rate": 1,
  "base_to_order_rate": 1,
  "customer_email": "davis@magebit.com",
  "customer_firstname": "D\u0101vis",
  "customer_group_id": 1,
  "customer_id": "2",
  "customer_is_guest": 0,
  "customer_lastname": "Magebit",
  "customer_note_notify": 1,
  "discount_amount": -90,
  "discount_description": "",
  "global_currency_code": "USD",
  "grand_total": 410,
  "discount_tax_compensation_amount": 0,
  "increment_id": "000000064",
  "is_virtual": 0,
  "order_currency_code": "USD",
  "quote_id": "30",
  "remote_ip": "127.0.0.1",
  "shipping_amount": 50,
  "shipping_description": "Flat Rate - Fixed",
  "shipping_discount_amount": 0,
  "shipping_discount_tax_compensation_amount": 0,
  "shipping_incl_tax": 50,
  "shipping_tax_amount": 0,
  "store_currency_code": "USD",
  "store_id": 1,
  "store_to_base_rate": 0,
  "store_to_order_rate": 0,
  "subtotal": 450,
  "subtotal_incl_tax": 450,
  "tax_amount": 0,
  "total_due": 410,
  "total_qty_ordered": 10,
  "weight": 0,
  "items": {
    "0 (Magento\\Sales\\Model\\Order\\Item\\Interceptor)": {
      "sku": "24-WB04",
      "name": "Push It Messenger Bag",
      "is_qty_decimal": false,
      "qty_ordered": 10,
      "quote_item_id": "58",
      "is_virtual": "0",
      "original_price": 45,
      "applied_rule_ids": "2,3",
      "price": 45,
      "base_price": 45,
      "tax_percent": 0,
      "tax_amount": 0,
      "row_weight": 0,
      "row_total": 450,
      "base_original_price": "45.0000",
      "base_tax_amount": 0,
      "base_row_total": 450,
      "store_id": 1,
      "discount_tax_compensation_amount": 0,
      "base_discount_tax_compensation_amount": 0,
      "product_id": "14",
      "product_type": "simple",
      "price_incl_tax": 45,
      "base_price_incl_tax": 45,
      "row_total_incl_tax": 450,
      "base_row_total_incl_tax": 450,
      "free_shipping": false,
      "discount_percent": 20,
      "discount_amount": 90,
      "base_discount_amount": 90,
      "product_options": {
        "info_buyRequest": {
          "uenc": "aHR0cDovL21hZ2UudGVzdC8,",
          "product": "14",
          "qty": 1
        }
      }
    }
  },
  "status_histories": [],
  "addresses": {
    "0 (Magento\\Sales\\Model\\Order\\Address)": {
      "customer_address_id": "4",
      "firstname": "D\u0101vis",
      "lastname": "Magebit",
      "company": "Magebit",
      "street": "Zigfrida Annas Meierovica 16\nZigfrida Annas Meierovica 16\nZigfrida Annas Meierovica 16",
      "city": "Riga",
      "region": "Aizputes novads",
      "region_id": "368",
      "postcode": "88766",
      "country_id": "LV",
      "telephone": "425421",
      "email": "davis@magebit.com",
      "address_type": "shipping",
      "quote_address_id": "129"
    },
    "1 (Magento\\Sales\\Model\\Order\\Address)": {
      "customer_address_id": 4,
      "firstname": "D\u0101vis",
      "lastname": "Magebit",
      "company": "Magebit",
      "street": "Zigfrida Annas Meierovica 16\nZigfrida Annas Meierovica 16\nZigfrida Annas Meierovica 16",
      "city": "Riga",
      "region": "Aizputes novads",
      "region_id": 368,
      "postcode": "88766",
      "country_id": "LV",
      "telephone": "425421",
      "email": "davis@magebit.com",
      "address_type": "billing",
      "quote_address_id": "131"
    }
  },
  "shipping_method": "flatrate_flatrate",
  "payment (Magento\\Sales\\Model\\Order\\Payment\\Interceptor)": {
    "method": "leanpay",
    "additional_information": {
      "method_title": "Leanpay Store"
    },
    "cc_exp_year": "0",
    "cc_ss_start_month": "0",
    "cc_ss_start_year": "0",
    "amount_ordered": 410,
    "base_amount_ordered": 410,
    "shipping_amount": 50,
    "base_shipping_amount": 50,
    "method_instance (Leanpay\\Payment\\Model\\Method\\LeanPay\\Interceptor)": {
      "info_instance (Magento\\Sales\\Model\\Order\\Payment\\Interceptor)": "*** RECURSION ***",
      "store": 1
    }
  }
}